dash_holoniq_components/Alert.py
dash_holoniq_components/Button.py
dash_holoniq_components/ButtonLink.py
dash_holoniq_components/Form.py
dash_holoniq_components/InputWithIcon.py
dash_holoniq_components/LayoutRouter.py
dash_holoniq_components/Location.py
dash_holoniq_components/PageTitle.py
dash_holoniq_components/PasswordWithShow.py
dash_holoniq_components/__init__.py
dash_holoniq_components/_imports_.py
dash_holoniq_components/dash_holoniq_components.dev.js
dash_holoniq_components/dash_holoniq_components.dev.js.map
dash_holoniq_components/dash_holoniq_components.min.js
dash_holoniq_components/dash_holoniq_components.min.js.map
dash_holoniq_components/metadata.json
dash_holoniq_components/package-info.json
examples/__init__.py
examples/form/__init__.py
examples/form/checkbox_form.py
examples/form/common.py
examples/form/default_page.py
examples/form/index.py
examples/form/signin_form.py
examples/form/user_profile.py
examples/multi_page/__init__.py
examples/multi_page/index.py
tests/__init__.py
tests/conftest.py
tests/title_test.py
tests/form/__init__.py
tests/form/alert_test.py
tests/form/checkbox_test.py
tests/form/default_test.py
utils/__init__.py
utils/logger.py
dash_holoniq_components-0.0.19.dist-info/LICENSE
dash_holoniq_components-0.0.19.dist-info/METADATA
dash_holoniq_components-0.0.19.dist-info/WHEEL
dash_holoniq_components-0.0.19.dist-info/top_level.txt
dash_holoniq_components-0.0.19.dist-info/RECORD
