Metadata-Version: 2.1
Name: dash-holoniq-components
Version: 0.0.19
Summary: Custom components for Plotly Dash
Home-page: UNKNOWN
Author: Steve Jones <jonesst2608@gmail.com>
License: MIT
Platform: UNKNOWN
Classifier: Framework :: Dash
License-File: LICENSE
Requires-Dist: dash (>=2.0.0)
Requires-Dist: dash-bootstrap-components (>=0.13.0)
